odoo/addons/website_event_ticket_published/README.rst
odoo/addons/website_event_ticket_published/__init__.py
odoo/addons/website_event_ticket_published/__manifest__.py
odoo/addons/website_event_ticket_published/i18n/es.po
odoo/addons/website_event_ticket_published/i18n/fr.po
odoo/addons/website_event_ticket_published/i18n/fr_FR.po
odoo/addons/website_event_ticket_published/i18n/it.po
odoo/addons/website_event_ticket_published/i18n/website_event_ticket_published.pot
odoo/addons/website_event_ticket_published/models/__init__.py
odoo/addons/website_event_ticket_published/models/event_ticket.py
odoo/addons/website_event_ticket_published/readme/CONFIGURE.rst
odoo/addons/website_event_ticket_published/readme/CONTRIBUTORS.rst
odoo/addons/website_event_ticket_published/readme/DESCRIPTION.rst
odoo/addons/website_event_ticket_published/static/description/icon.png
odoo/addons/website_event_ticket_published/static/description/index.html
odoo/addons/website_event_ticket_published/templates/event_ticket.xml
odoo/addons/website_event_ticket_published/views/event_ticket.xml
odoo_addon_website_event_ticket_published-15.0.1.0.0.11.dist-info/METADATA
odoo_addon_website_event_ticket_published-15.0.1.0.0.11.dist-info/WHEEL
odoo_addon_website_event_ticket_published-15.0.1.0.0.11.dist-info/top_level.txt
odoo_addon_website_event_ticket_published-15.0.1.0.0.11.dist-info/RECORD
